MANIFEST.in
README.md
setup.py
etc/neutron/policy.d/lbaas_device.json
f5_openstack_lbaasv2_inventory.egg-info/PKG-INFO
f5_openstack_lbaasv2_inventory.egg-info/SOURCES.txt
f5_openstack_lbaasv2_inventory.egg-info/dependency_links.txt
f5_openstack_lbaasv2_inventory.egg-info/entry_points.txt
f5_openstack_lbaasv2_inventory.egg-info/top_level.txt
neutron_lbaas_inventory/__init__.py
neutron_lbaas_inventory/common/__init__.py
neutron_lbaas_inventory/common/constants.py
neutron_lbaas_inventory/common/exceptions.py
neutron_lbaas_inventory/db/__init__.py
neutron_lbaas_inventory/db/inventory_db.py
neutron_lbaas_inventory/db/migration/__init__.py
neutron_lbaas_inventory/db/migration/alembic_migrations/__init__.py
neutron_lbaas_inventory/db/migration/alembic_migrations/env.py
neutron_lbaas_inventory/db/migration/alembic_migrations/inventory_init_ops.py
neutron_lbaas_inventory/db/migration/alembic_migrations/versions/__init__.py
neutron_lbaas_inventory/db/migration/alembic_migrations/versions/pike_initial.py
neutron_lbaas_inventory/db/models/__init__.py
neutron_lbaas_inventory/db/models/head.py
neutron_lbaas_inventory/db/models/inventory.py
neutron_lbaas_inventory/extensions/__init__.py
neutron_lbaas_inventory/extensions/base.py
neutron_lbaas_inventory/extensions/lbaasdevice.py
neutron_lbaas_inventory/extensions/lbaasextensions.py
neutron_lbaas_inventory/plugins/__init__.py
neutron_lbaas_inventory/plugins/lbaasextensions.py