Metadata-Version: 1.1
Name: f5-openstack-lbaasv2-inventory
Version: 1.2.0
Summary: F5 Networks device inventory for OpenStack services
Home-page: UNKNOWN
Author: F5 Networks
Author-email: openstack@f5.com
License: Apache License, Version 2.0
Platform: UNKNOWN
Classifier: Environment :: OpenStack
Classifier: Intended Audience :: Information Technology
Classifier: Intended Audience :: System Administrators
Classifier: License :: OSI Approved :: Apache Software License
Classifier: Operating System :: POSIX :: Linux
Classifier: Programming Language :: Python
Classifier: Programming Language :: Python :: 2
Classifier: Programming Language :: Python :: 2.7
